odoo/addons/l10n_ch_mis_reports/README.rst
odoo/addons/l10n_ch_mis_reports/__init__.py
odoo/addons/l10n_ch_mis_reports/__manifest__.py
odoo/addons/l10n_ch_mis_reports/data/mis_report.xml
odoo/addons/l10n_ch_mis_reports/data/mis_report_kpi_bs.xml
odoo/addons/l10n_ch_mis_reports/data/mis_report_kpi_pl.xml
odoo/addons/l10n_ch_mis_reports/data/mis_report_style.xml
odoo/addons/l10n_ch_mis_reports/i18n/l10n_ch_mis_reports.pot
odoo/addons/l10n_ch_mis_reports/readme/CONFIGURE.rst
odoo/addons/l10n_ch_mis_reports/readme/CONTRIBUTORS.rst
odoo/addons/l10n_ch_mis_reports/readme/DESCRIPTION.rst
odoo/addons/l10n_ch_mis_reports/readme/INSTALL.rst
odoo/addons/l10n_ch_mis_reports/readme/ROADMAP.rst
odoo/addons/l10n_ch_mis_reports/readme/USAGE.rst
odoo/addons/l10n_ch_mis_reports/static/description/icon.png
odoo/addons/l10n_ch_mis_reports/static/description/index.html
odoo_addon_l10n_ch_mis_reports-16.0.1.0.0.2.dist-info/METADATA
odoo_addon_l10n_ch_mis_reports-16.0.1.0.0.2.dist-info/WHEEL
odoo_addon_l10n_ch_mis_reports-16.0.1.0.0.2.dist-info/top_level.txt
odoo_addon_l10n_ch_mis_reports-16.0.1.0.0.2.dist-info/RECORD
